async_event_bus/__init__.py
async_event_bus/event_bus.py
async_event_bus/event/__init__.py
async_event_bus/event/async_event_callback.py
async_event_bus/event/event.py
async_event_bus/event/event_callback.py
async_event_bus/event/event_callback_container.py
async_event_bus/event/event_callback_factory.py
async_event_bus/event/sync_event_callback.py
async_event_bus/module/__init__.py
async_event_bus/module/base_bus.py
async_event_bus/module/base_module.py
async_event_bus/module/bus_filter.py
async_event_bus/module/bus_inject.py
async_event_bus/module/module_exceptions.py
async_event_bus-0.4.0.dist-info/licenses/LICENSE
async_event_bus-0.4.0.dist-info/METADATA
async_event_bus-0.4.0.dist-info/WHEEL
async_event_bus-0.4.0.dist-info/top_level.txt
async_event_bus-0.4.0.dist-info/RECORD
