Metadata-Version: 2.4
Name: async-event-bus
Version: 0.4.0
Summary: A simple python event bus for python3
Author-email: Half_nothing <Half_nothing@163.com>
License: MIT
Keywords: python,event-bus
Classifier: License :: OSI Approved :: MIT License
Classifier: Development Status :: 4 - Beta
Classifier: Programming Language :: Python :: 3
Classifier: Programming Language :: Python :: 3.12
Classifier: Environment :: Console
Classifier: Intended Audience :: Developers
Classifier: Natural Language :: Chinese (Simplified)
Requires-Python: >=3.12
License-File: LICENSE
Requires-Dist: loguru>=0.7.3
Provides-Extra: dev
Requires-Dist: setuptools>=80.9.0; extra == "dev"
Requires-Dist: pytest>=8.4.1; extra == "dev"
Requires-Dist: pytest-html>=4.1.1; extra == "dev"
Requires-Dist: pytest-asyncio>=1.1.0; extra == "dev"
Dynamic: license-file
